data_quality_check/__init__.py
data_quality_check/config.py
data_quality_check/constants.py
data_quality_check/profile_report.py
data_quality_check/version.py
data_quality_check/controller/__init__.py
data_quality_check/controller/console.py
data_quality_check/core/__init__.py
data_quality_check/core/qc_dataframe.py
data_quality_check/core/runner.py
data_quality_check/core/checks/__init__.py
data_quality_check/core/checks/check.py
data_quality_check/core/checks/customized_check.py
data_quality_check/core/checks/general_check.py
data_quality_check/core/expectations/__init__.py
data_quality_check/core/expectations/expect_column_to_exist.py
data_quality_check/core/expectations/expectation.py
data_quality_check/profiler/__init__.py
data_quality_check/profiler/combined_profiler.py
data_quality_check/profiler/customized_profiler.py
data_quality_check/profiler/general_profiler.py
data_quality_check/report/__init__.py
data_quality_check/report/report.py
data_quality_check/report/renders/__init__.py
data_quality_check/report/renders/html/__init__.py
data_quality_check/report/renders/html/formatters.py
data_quality_check/report/renders/html/render.py
data_quality_check/report/renders/html/templates.py
data_quality_check/report/renders/html/templates/customized_profiler_code_check_template.html
data_quality_check/report/renders/html/templates/debug.html
data_quality_check/report/renders/html/templates/general_profiler_template.html
data_quality_check/report/renders/html/templates/page_bottom.html
data_quality_check/report/renders/html/templates/page_top.html
data_quality_check/report/renders/json/__init__.py
data_quality_check/udf/__init__.py
data_quality_check/udf/udf.py
data_quality_check/udf/udf_test.py
data_quality_check/utils/__init__.py
data_quality_check/utils/cache.py
data_quality_check/utils/paths.py
data_quality_check-0.0.20.dist-info/METADATA
data_quality_check-0.0.20.dist-info/WHEEL
data_quality_check-0.0.20.dist-info/entry_points.txt
data_quality_check-0.0.20.dist-info/top_level.txt
data_quality_check-0.0.20.dist-info/RECORD
