Metadata-Version: 2.1
Name: data-quality-check
Version: 0.0.20
Summary: Spark data quality check tool
Home-page: UNKNOWN
Author: Guanlong Zhou
Author-email: markgzhou@outlook.com
License: UNKNOWN
Keywords: spark data-quality-check python jupyter ipython
Platform: UNKNOWN
Classifier: Development Status :: 3 - Alpha
Classifier: License :: OSI Approved :: MIT License
Classifier: Environment :: Console
Classifier: Operating System :: OS Independent
Classifier: Intended Audience :: Developers
Classifier: Intended Audience :: Science/Research
Classifier: Topic :: Software Development :: Libraries :: Python Modules
Classifier: Operating System :: OS Independent
Classifier: Framework :: IPython
Classifier: Programming Language :: Python :: 3
Requires-Python: >=3.7
Requires-Dist: PyYAML (~=6.0)
Requires-Dist: pydantic (~=1.6)
Requires-Dist: requests (~=2.6)
Requires-Dist: jinja2 (~=3.0.3)
Requires-Dist: markupsafe (~=2.1.0)
